django_wechat_wallet-0.2.0.dist-info/DESCRIPTION.rst
django_wechat_wallet-0.2.0.dist-info/METADATA
django_wechat_wallet-0.2.0.dist-info/RECORD
django_wechat_wallet-0.2.0.dist-info/WHEEL
django_wechat_wallet-0.2.0.dist-info/metadata.json
django_wechat_wallet-0.2.0.dist-info/top_level.txt
wallet/__init__.py
wallet/admin.py
wallet/api.py
wallet/apps.py
wallet/models.py
wallet/tests.py
wallet/urls.py
wallet/views.py
wallet/locale/zh_Hans/LC_MESSAGES/django.mo
wallet/locale/zh_Hans/LC_MESSAGES/django.po
wallet/templates/wallet/base.html
wallet/templates/wallet/index.html
wallet/templates/wallet/log_list.html
